comwatt_client_legacy/__init__.py
comwatt_client_legacy/client.py
comwatt_client_legacy-0.1.2.dist-info/METADATA
comwatt_client_legacy-0.1.2.dist-info/WHEEL
comwatt_client_legacy-0.1.2.dist-info/top_level.txt
comwatt_client_legacy-0.1.2.dist-info/RECORD
